RoManTools/__init__.py
RoManTools/chunker.py
RoManTools/config.py
RoManTools/constants.py
RoManTools/conversion.py
RoManTools/data_loader.py
RoManTools/main.py
RoManTools/syllable.py
RoManTools/utils.py
RoManTools/word.py
RoManTools/data/conversion_mapping.csv
RoManTools/data/pyDF.csv
RoManTools/data/stopwords.txt
RoManTools/data/wgDF.csv
RoManTools-0.2.0b2.dist-info/LICENSE
RoManTools-0.2.0b2.dist-info/METADATA
RoManTools-0.2.0b2.dist-info/WHEEL
RoManTools-0.2.0b2.dist-info/entry_points.txt
RoManTools-0.2.0b2.dist-info/top_level.txt
RoManTools-0.2.0b2.dist-info/RECORD
