Metadata-Version: 2.2
Name: RoManTools
Version: 0.2.0b2
Summary: Tools for processing and converting Romanized Mandarin text
Author-email: Jeff Heller <jsheller@princeton.edu>
License: GPL-3.0 license
Project-URL: Homepage, https://github.com/JHGFD82/RoManTools
Project-URL: Documentation, https://github.com/JHGFD82/RoManTools/tree/main/docs
Project-URL: Source, https://github.com/JHGFD82/RoManTools
Project-URL: Tracker, https://github.com/JHGFD82/RoManTools/issues
Classifier: Programming Language :: Python :: 3
Classifier: License :: OSI Approved :: GNU General Public License v3 (GPLv3)
Classifier: Operating System :: OS Independent
Classifier: Intended Audience :: Education
Classifier: Intended Audience :: Science/Research
Classifier: Topic :: Text Processing :: Linguistic
Requires-Python: >=3.8
License-File: LICENSE
